Lab4/testBench/BIC.v
module BIC(sr_clk, enable, reset, finish, state);
	input sr_clk;
	input enable;
	input reset;
	output reg finish;
	output reg [3:0] state;

	always @(posedge sr_clk or reset or ~enable) begin
		if (reset) begin
			state <= 4'b0000;
			finish <= 1'b0;
			end
		else if (enable) begin
			state <= state + 1'b1;
			finish <= finish;
			if (state == 4'b1010) begin
				finish <= 1'b1;
				state <= 4'b1010;
			end
		end
		else begin
			state <= 4'b0000;
			finish <= 1'b0;
			end
	end
endmodule

Lab4/testBench/BIC_testBench.v
`include "BIC.v"

module BIC_testBench ();

    // connext the two modules
        wire sr_clk, reset, enable, finish;
        wire [3:0] state;

    // declare an instance of the AND module
    BIC bic (sr_clk, enable, reset, finish, state);

    // Running the GUI part of simulation
    BIC_Tester aTester (sr_clk, enable, reset, finish, state);

    // file for gtkwave

    initial
    begin
        $dumpfile("BIC.vcd");
        $dumpvars(1, bic);
    end

endmodule

module BIC_Tester (sr_clk, enable, reset, finish, state);
    output reg sr_clk, reset, enable;
    input finish;
    input [3:0] state;

    parameter stimDelay = 10;

    // generate a clock
    always #(stimDelay/2) sr_clk = ~sr_clk;

    initial // Response
    begin
        sr_clk = 'b0;
    end

    always @(posedge sr_clk) // Stimulus
    begin
                    //reset = 'b0;
        #stimDelay    reset <= 1'b0;
        #stimDelay
        reset <= 1'b1;
        #stimDelay
        reset <= 1'b0;
	   enable <= 1'b1;
        #(10*stimDelay)
        #(32*stimDelay)
        #(32*stimDelay)
        enable <= 1'b0;
        #(32*stimDelay)

        $stop;
        $finish;
    end

endmodule

Lab4/testBench/BIC.vcd
$date
	Mon May 30 18:02:05 2016
$end
$version
	Icarus Verilog
$end
$timescale
	1s
$end
$scope module BIC_testBench $end
$scope module bic $end
$var wire 1 ! enable $end
$var wire 1 " reset $end
$var wire 1 # sr_clk $end
$var reg 1 $ finish $end
$var reg 4 % state [3:0] $end
$upscope $end
$upscope $end
$enddefinitions $end
#0
$dumpvars
bx %
x$
0#
x"
x!
$end
#5
0$
b0 %
1#
#10
0#
#15
0"
1#
#20
0#
#25
1"
1#
#30
0#
#35
b1 %
1!
0"
1#
#40
0#
#45
b10 %
1#
#50
0#
#55
b11 %
1#
#60
0#
#65
b100 %
1#
#70
0#
#75
b101 %
1#
#80
0#
#85
b110 %
1#
#90
0#
#95
b111 %
1#
#100
0#
#105
b1000 %
1#
#110
0#
#115
b1001 %
1#
#120
0#
#125
b1010 %
1#
#130
0#
#135
1$
b1010 %
1#
#140
0#
#145
b1010 %
1#
#150
0#
#155
b1010 %
1#
#160
0#
#165
b1010 %
1#
#170
0#
#175
b1010 %
1#
#180
0#
#185
b1010 %
1#
#190
0#
#195
b1010 %
1#
#200
0#
#205
b1010 %
1#
#210
0#
#215
b1010 %
1#
#220
0#
#225
b1010 %
1#
#230
0#
#235
b1010 %
1#
#240
0#
#245
b1010 %
1#
#250
0#
#255
b1010 %
1#
#260
0#
#265
b1010 %
1#
#270
0#
#275
b1010 %
1#
#280
0#
#285
b1010 %
1#
#290
0#
#295
b1010 %
1#
#300
0#
#305
b1010 %
1#
#310
0#
#315
b1010 %
1#
#320
0#
#325
b1010 %
1#
#330
0#
#335
b1010 %
1#
#340
0#
#345
b1010 %
1#
#350
0#
#355
b1010 %
1#
#360
0#
#365
b1010 %
1#
#370
0#
#375
b1010 %
1#
#380
0#
#385
b1010 %
1#
#390
0#
#395
b1010 %
1#
#400
0#
#405
b1010 %
1#
#410
0#
#415
b1010 %
1#
#420
0#
#425
b1010 %
1#
#430
0#
#435
b1010 %
1#
#440
0#
#445
b1010 %
1#
#450
0#
#455
b1010 %
1#
#460
0#
#465
b1010 %
1#
#470
0#
#475
b1010 %
1#
#480
0#
#485
b1010 %
1#
#490
0#
#495
b1010 %
1#
#500
0#
#505
b1010 %
1#
#510
0#
#515
b1010 %
1#
#520
0#
#525
b1010 %
1#
#530
0#
#535
b1010 %
1#
#540
0#
#545
b1010 %
1#
#550
0#
#555
b1010 %
1#
#560
0#
#565
b1010 %
1#
#570
0#
#575
b1010 %
1#
#580
0#
#585
b1010 %
1#
#590
0#
#595
b1010 %
1#
#600
0#
#605
b1010 %
1#
#610
0#
#615
b1010 %
1#
#620
0#
#625
b1010 %
1#
#630
0#
#635
b1010 %
1#
#640
0#
#645
b1010 %
1#
#650
0#
#655
b1010 %
1#
#660
0#
#665
b1010 %
1#
#670
0#
#675
b1010 %
1#
#680
0#
#685
b1010 %
1#
#690
0#
#695
b1010 %
1#
#700
0#
#705
b1010 %
1#
#710
0#
#715
b1010 %
1#
#720
0#
#725
b1010 %
1#
#730
0#
#735
b1010 %
1#
#740
0#
#745
b1010 %
1#
#750
0#
#755
b1010 %
1#
#760
0#
#765
b1010 %
1#
#770
0#
#775
b1010 %
0!
1#
#780
0#
#785
0$
b0 %
1#
