Lab4/testBench/BSC.v
module BSC(reset, enable, clk, sr_clk);
	input reset;
	input enable;
	input clk;
	output reg sr_clk;
	reg [3:0] state;
	always @(posedge clk) begin
		if (reset) begin
			state <= 4'b0000;
			sr_clk <= 1'b0;
		end
		else if (enable) begin
			state <= state + 1'b1;
			if (state == 4'b1000)
				sr_clk <= 1'b1;
			else 
				sr_clk <= 1'b0;
		end
		else begin
			state <= 4'b0000;
			sr_clk <= 1'b0;
		end
	end
endmodule

Lab4/testBench/BSC_testBench.v
`include "BSC.v"

module BSC_testBench ();

    // connext the two modules
        wire sr_clk, clk, reset, enable;

    // declare an instance of the AND module
    BSC bsc (reset, enable, clk, sr_clk);

    // Running the GUI part of simulation
    BSC_Tester aTester (reset, enable, clk, sr_clk);

    // file for gtkwave

    initial
    begin
        $dumpfile("BSC.vcd");
        $dumpvars(1, bsc);
    end

endmodule

module BSC_Tester (reset, enable, clk, sr_clk);
    output reg clk, reset, enable;
    input sr_clk;

    parameter stimDelay = 10;

    // generate a clock
    always #(stimDelay/2) clk = ~clk;

    initial // Response
    begin
        clk = 'b0;
    end

    always @(posedge clk) // Stimulus
    begin
                    //reset = 'b0;
        #stimDelay    reset <= 1'b0;
        #stimDelay
        reset <= 1'b1;
        #stimDelay
        reset <= 1'b0;
	   enable <= 1'b1;
        #(10*stimDelay)
        #(32*stimDelay)
        #(32*stimDelay)
        enable <= 1'b0;
        #(32*stimDelay)

        $stop;
        $finish;
    end

endmodule

Lab4/testBench/BSC.vcd
$date
	Mon May 30 16:34:17 2016
$end
$version
	Icarus Verilog
$end
$timescale
	1s
$end
$scope module BSC_testBench $end
$scope module bsc $end
$var wire 1 ! clk $end
$var wire 1 " enable $end
$var wire 1 # reset $end
$var reg 1 $ sr_clk $end
$var reg 4 % state [3:0] $end
$upscope $end
$upscope $end
$enddefinitions $end
#0
$dumpvars
bx %
x$
x#
x"
0!
$end
#5
0$
b0 %
1!
#10
0!
#15
0#
1!
#20
0!
#25
1#
1!
#30
0!
#35
1"
0#
1!
#40
0!
#45
b1 %
1!
#50
0!
#55
b10 %
1!
#60
0!
#65
b11 %
1!
#70
0!
#75
b100 %
1!
#80
0!
#85
b101 %
1!
#90
0!
#95
b110 %
1!
#100
0!
#105
b111 %
1!
#110
0!
#115
b1000 %
1!
#120
0!
#125
1$
b1001 %
1!
#130
0!
#135
0$
b1010 %
1!
#140
0!
#145
b1011 %
1!
#150
0!
#155
b1100 %
1!
#160
0!
#165
b1101 %
1!
#170
0!
#175
b1110 %
1!
#180
0!
#185
b1111 %
1!
#190
0!
#195
b0 %
1!
#200
0!
#205
b1 %
1!
#210
0!
#215
b10 %
1!
#220
0!
#225
b11 %
1!
#230
0!
#235
b100 %
1!
#240
0!
#245
b101 %
1!
#250
0!
#255
b110 %
1!
#260
0!
#265
b111 %
1!
#270
0!
#275
b1000 %
1!
#280
0!
#285
1$
b1001 %
1!
#290
0!
#295
0$
b1010 %
1!
#300
0!
#305
b1011 %
1!
#310
0!
#315
b1100 %
1!
#320
0!
#325
b1101 %
1!
#330
0!
#335
b1110 %
1!
#340
0!
#345
b1111 %
1!
#350
0!
#355
b0 %
1!
#360
0!
#365
b1 %
1!
#370
0!
#375
b10 %
1!
#380
0!
#385
b11 %
1!
#390
0!
#395
b100 %
1!
#400
0!
#405
b101 %
1!
#410
0!
#415
b110 %
1!
#420
0!
#425
b111 %
1!
#430
0!
#435
b1000 %
1!
#440
0!
#445
1$
b1001 %
1!
#450
0!
#455
0$
b1010 %
1!
#460
0!
#465
b1011 %
1!
#470
0!
#475
b1100 %
1!
#480
0!
#485
b1101 %
1!
#490
0!
#495
b1110 %
1!
#500
0!
#505
b1111 %
1!
#510
0!
#515
b0 %
1!
#520
0!
#525
b1 %
1!
#530
0!
#535
b10 %
1!
#540
0!
#545
b11 %
1!
#550
0!
#555
b100 %
1!
#560
0!
#565
b101 %
1!
#570
0!
#575
b110 %
1!
#580
0!
#585
b111 %
1!
#590
0!
#595
b1000 %
1!
#600
0!
#605
1$
b1001 %
1!
#610
0!
#615
0$
b1010 %
1!
#620
0!
#625
b1011 %
1!
#630
0!
#635
b1100 %
1!
#640
0!
#645
b1101 %
1!
#650
0!
#655
b1110 %
1!
#660
0!
#665
b1111 %
1!
#670
0!
#675
b0 %
1!
#680
0!
#685
b1 %
1!
#690
0!
#695
b10 %
1!
#700
0!
#705
b11 %
1!
#710
0!
#715
b100 %
1!
#720
0!
#725
b101 %
1!
#730
0!
#735
b110 %
1!
#740
0!
#745
b111 %
1!
#750
0!
#755
b1000 %
1!
#760
0!
#765
1$
b1001 %
1!
#770
0!
#775
0$
b1010 %
0"
1!
#780
0!
#785
b0 %
1!
