Lab4/testBench/PISO.v
module PISO(sr_clk, clk, reset, data_in, data_out, load); // Parallel in -> Serial Out (10 bits)

	input sr_clk, clk, reset, load;
	input [7:0] data_in;
	output reg data_out;

	reg [9:0] Q_out;
	initial Q_out = 10'b1000000000;
	// reg bitStream;
	reg ps_load, ns_load;

	// Always block conducts parallel load
	always @(posedge clk) begin
			if (reset) begin
				Q_out[9:0] <= 10'b1000000000;
			end
			else if (load && ps_load != load) begin
				Q_out[9] = 1'b1;
				Q_out[8:1] = data_in;
				Q_out[0] = 1'b0;
			end
			else if (sr_clk) begin
				data_out = Q_out[9];
				Q_out[9] <= Q_out[8];
				Q_out[8] <= Q_out[7];
				Q_out[7] <= Q_out[6];
				Q_out[6] <= Q_out[5];
				Q_out[5] <= Q_out[4];
				Q_out[4] <= Q_out[3];
				Q_out[3] <= Q_out[2];
				Q_out[2] <= Q_out[1];
				Q_out[1] <= Q_out[0];
				Q_out[0] <= 1'b0;
		 end
		 ps_load <= ns_load;
		 ns_load <= load;
	end
endmodule

Lab4/testBench/PISO_testBench.v
`include "PISO.v"

module PISO_testBench ();

    // connext the two modules
    wire [7:0] data_in;
    wire sr_clk, clk, reset, data_out, load;

    // declare an instance of the AND module
    PISO tx (sr_clk, clk, reset, data_in, data_out, load);

    // Running the GUI part of simulation
    PISO_Tester aTester (sr_clk, clk, reset, data_in, data_out, load);

    // file for gtkwave

    initial
    begin
        $dumpfile("piso.vcd");
        $dumpvars(1, tx);
    end

endmodule

module PISO_Tester (sr_clk, clk, reset, data_in, data_out, load);
    output reg sr_clk, clk, reset, load;
    output reg [7:0] data_in;
    input data_out;

    parameter stimDelay = 10;

    // generate a clock
    always #(stimDelay/2) clk = ~clk;

    initial // Response
    begin
        // $display("\t\t clk rst_n \t out \t   Time ");
        $monitor("\t %b ", data_out, sr_clk, $time);
        clk = 'b0;
    end

    always @(posedge clk) // Stimulus
    begin
                    //reset = 'b0;
        #stimDelay    reset <= 1'b0;
        #stimDelay
        reset <= 1'b1;
        #stimDelay
        reset <= 1'b0;
        #(10*stimDelay)
        load = 1'b0;
        sr_clk = 1'b0;
        #stimDelay
        reset <= 1'b0;
        data_in <= 8'b0101010;
        load = 1'b1;
        #stimDelay
        sr_clk = 1'b1;
        #(8*stimDelay)
        sr_clk = 1'b0;
        #stimDelay
        sr_clk = 1'b1;
        #(8*stimDelay)
        sr_clk = 1'b0;
        #stimDelay
        sr_clk = 1'b1;
        #(8*stimDelay)
        sr_clk = 1'b0;
        load = 1'b0;
        #stimDelay
        #stimDelay
        load = 1'b1;
        data_in <= 8'b11001001;
        #stimDelay
        sr_clk = 1'b1;
        #(8*stimDelay)
        sr_clk = 1'b0;
        #stimDelay
        sr_clk = 1'b1;
        #(8*stimDelay)
        sr_clk = 1'b0;
        #stimDelay
        sr_clk = 1'b1;
        #(8*stimDelay)
        sr_clk = 1'b0;

        load = 1'b0;
        #(32*stimDelay)
        $stop;
        $finish;
    end

endmodule

Lab4/testBench/piso.vcd
$date
	Fri May 27 17:24:23 2016
$end
$version
	Icarus Verilog
$end
$timescale
	1s
$end
$scope module PISO_testBench $end
$scope module tx $end
$var wire 1 ! clk $end
$var wire 8 " data_in [7:0] $end
$var wire 1 # load $end
$var wire 1 $ reset $end
$var wire 1 % sr_clk $end
$var reg 10 & Q_out [9:0] $end
$var reg 1 ' data_out $end
$var reg 1 ( ns_load $end
$var reg 1 ) ps_load $end
$upscope $end
$upscope $end
$enddefinitions $end
#0
$dumpvars
x)
x(
x'
b1000000000 &
x%
x$
x#
bx "
0!
$end
#5
1!
#10
0!
#15
0$
1!
#20
0!
#25
1$
1!
#30
0!
#35
0(
1!
0%
0#
#40
0!
#45
1(
0)
b101010 "
0$
1!
1#
#50
0!
#55
1)
b1001010100 &
1!
1%
#60
0!
#65
b10101000 &
1'
1!
#70
0!
#75
b101010000 &
0'
1!
#80
0!
#85
b1010100000 &
1!
#90
0!
#95
b101000000 &
1'
1!
#100
0!
#105
b1010000000 &
0'
1!
#110
0!
#115
b100000000 &
1'
1!
#120
0!
#125
b1000000000 &
0'
1!
#130
0!
#135
1!
0%
#140
0!
#145
b0 &
1'
1!
1%
#150
0!
#155
0'
1!
#160
0!
#165
1!
#170
0!
#175
1!
#180
0!
#185
1!
#190
0!
#195
1!
#200
0!
#205
1!
#210
0!
#215
1!
#220
0!
#225
1!
0%
#230
0!
#235
1!
1%
#240
0!
#245
1!
#250
0!
#255
1!
#260
0!
#265
1!
#270
0!
#275
1!
#280
0!
#285
1!
#290
0!
#295
1!
#300
0!
#305
1!
#310
0!
#315
0(
1!
0#
0%
#320
0!
#325
0)
1!
#330
0!
#335
1(
b11001001 "
b1001010100 &
1!
1#
#340
0!
#345
1)
b1110010010 &
1!
1%
#350
0!
#355
b1100100100 &
1'
1!
#360
0!
#365
b1001001000 &
1!
#370
0!
#375
b10010000 &
1!
#380
0!
#385
b100100000 &
0'
1!
#390
0!
#395
b1001000000 &
1!
#400
0!
#405
b10000000 &
1'
1!
#410
0!
#415
b100000000 &
0'
1!
#420
0!
#425
1!
0%
#430
0!
#435
b1000000000 &
1!
1%
#440
0!
#445
b0 &
1'
1!
#450
0!
#455
0'
1!
#460
0!
#465
1!
#470
0!
#475
1!
#480
0!
#485
1!
#490
0!
#495
1!
#500
0!
#505
1!
#510
0!
#515
1!
0%
#520
0!
#525
1!
1%
#530
0!
#535
1!
#540
0!
#545
1!
#550
0!
#555
1!
#560
0!
#565
1!
#570
0!
#575
1!
#580
0!
#585
1!
#590
0!
#595
1!
#600
0!
#605
0(
1!
0#
0%
#610
0!
#615
0)
1!
