Lab4/testBench/SIPO.v
module SIPO(data_in, sr_clk, reset, finish, data_out); // Serial In -> Parallel Out (10 bits)
	input sr_clk, reset;
	input data_in;
	input finish;
	output reg [7:0] data_out;

	reg [9:0] Q;

	always @(posedge sr_clk or reset) begin
		if (reset)
			Q <= 10'b0000000000;
		else begin
			Q[0] <= data_in;
			Q[1] <= Q[0];
			Q[2] <= Q[1];
			Q[3] <= Q[2];
			Q[4] <= Q[3];
			Q[5] <= Q[4];
			Q[6] <= Q[5];
			Q[7] <= Q[6];
			Q[8] <= Q[7];
			Q[9] <= Q[8];
		end
	end

	always @(posedge finish) begin
		data_out[0] <= Q[1];
		data_out[1] <= Q[2];
		data_out[2] <= Q[3];
		data_out[3] <= Q[4];
		data_out[4] <= Q[5];
		data_out[5] <= Q[6];
		data_out[6] <= Q[7];
		data_out[7] <= Q[8];
	end
endmodule

Lab4/testBench/BIC.v
module BIC(sr_clk, enable, reset, finish, state);
	input sr_clk;
	input enable;
	input reset;
	output reg finish;
	output reg [3:0] state;

	always @(posedge sr_clk or reset or ~enable) begin
		if (reset) begin
			state <= 4'b0000;
			finish <= 1'b0;
			end
		else if (enable) begin
			state <= state + 1'b1;
			finish <= finish;
			if (state == 4'b1010) begin
				finish <= 1'b1;
				state <= 4'b1010;
			end
		end
		else begin
			state <= 4'b0000;
			finish <= 1'b0;
			end
	end
endmodule

Lab4/testBench/BSC.v
module BSC(reset, enable, clk, sr_clk);
	input reset;
	input enable;
	input clk;
	output reg sr_clk;
	reg [3:0] state;
	always @(posedge clk) begin
		if (reset) begin
			state <= 4'b0000;
			sr_clk <= 1'b0;
		end
		else if (enable) begin
			state <= state + 1'b1;
			if (state == 4'b1000)
				sr_clk <= 1'b1;
			else 
				sr_clk <= 1'b0;
		end
		else begin
			state <= 4'b0000;
			sr_clk <= 1'b0;
		end
	end
endmodule

Lab4/testBench/start_detect.v
module start_detect(data_in, reset, clk, state, enable);
	input data_in;
	input clk;
	input reset;
	input [3:0] state;
	output enable;

	reg enable, ns;

	always @(*) begin
		case(enable)
			1'b0: if (state == 4'b0000 & data_in == 1'b1)
						ns = 1'b1;
					else
						ns = 1'b0;
		   1'b1: if (state == 4'b1011 & data_in == 1'b0) // Wait for another state to 4'b1011 to generate the enable long enough
						ns = 1'b0;
					else
						ns = 1'b1;
		endcase
	end


	always @(posedge clk) begin
		if (reset)
			enable <= 1'b0;
		else
			enable <= ns;
		end
endmodule

Lab4/testBench/buffer.v
module buffer(input clk, reset, data_in, output data_out);
	reg q;
	assign data_out = q;
	 
	always @(posedge clk) begin
		if (reset) begin
			q <= 1;
		end else begin
			q <= data_in;
		end
	end
endmodule

Lab4/testBench/receive.v
module receive(data_in, reset, clk, data_out, finish);
	input data_in, reset, clk;
	output [7:0] data_out;
	output finish;

	wire data;
	wire [3:0] state;
	wire enable;
	wire sr_clk;

	buffer b(.clk, .reset, .data_in, .data_out(data));
	start_detect detect(.data_in(data), .reset, .clk, .state(state), .enable);
	BSC bsc(.reset, .enable, .clk, .sr_clk);
	BIC bic(.sr_clk, .enable, .reset, .finish, .state(state));
	SIPO sipo(.data_in(data), .sr_clk, .reset, .finish, .data_out);

endmodule

Lab4/testBench/receive_testBench.v
`include "start_detect.v"
`include "BSC.v"
`include "BIC.v"
`include "buffer.v"
`include "SIPO.v"
`include "receive.v"

module receive_testBench ();

    // connext the two modules
    wire [7:0] data_out;
    wire enable, reset, clk, data_in, finish;

    // declare an instance of the AND module
    receive rx (data_in, reset, clk, data_out, finish);

    // Running the GUI part of simulation
    receive_Tester aTester (data_in, reset, clk, data_out, finish);

    // file for gtkwave

    initial
    begin
        $dumpfile("receive.vcd");
        $dumpvars(1, rx);
    end

endmodule

module receive_Tester (data_in, reset, clk, data_out, finish);
    input [7:0] data_out;
    input finish;
    output reg data_in, reset, clk;

    parameter stimDelay = 20;

    // generate a clock
    always #(stimDelay/2) clk = ~clk;

    initial // Response
    begin
        // $display("\t\t clk rst_n \t out \t   Time ");
        $monitor("\t %b ", data_out, finish, $time);
        clk = 'b0;
    end

    always @(posedge clk) // Stimulus
    begin
                    //reset = 'b0;
        #stimDelay    reset <= 'b1;
        #stimDelay
        reset <= 'b0;
        data_in <= 'b1;
        #stimDelay
        reset <= 'b0;
        #(14*stimDelay)
        data_in <= 'b0;
        #(16*stimDelay)
        data_in <= 'b1;
        #(16*stimDelay)
        data_in <= 'b0;
        #(16*stimDelay)
        data_in <= 'b1;
        #(16*stimDelay)
        data_in <= 'b0;
        #(16*stimDelay)
        data_in <= 'b1;
        #(16*stimDelay)
        data_in <= 'b0;
        #(16*stimDelay)
        data_in <= 'b1;
        #(16*stimDelay)
        data_in <= 'b0;
        #stimDelay
        #stimDelay
        #(32*stimDelay)
        $stop;
        $finish;
    end

endmodule

Lab4/testBench/receive.vcd
$date
	Mon May 30 17:20:46 2016
$end
$version
	Icarus Verilog
$end
$timescale
	1s
$end
$scope module receive_testBench $end
$scope module rx $end
$var wire 1 ! clk $end
$var wire 1 " data_in $end
$var wire 1 # reset $end
$var wire 4 $ state [3:0] $end
$var wire 1 % sr_clk $end
$var wire 1 & finish $end
$var wire 1 ' enable $end
$var wire 8 ( data_out [7:0] $end
$var wire 1 ) data $end
$upscope $end
$upscope $end
$enddefinitions $end
#0
$dumpvars
x)
bx (
x'
x&
x%
bx $
x#
x"
0!
$end
#10
0%
1!
#20
0!
#30
0&
b0 $
1#
1!
#40
0!
#50
1)
0'
1"
0#
1!
#60
0!
#70
1'
1!
#80
0!
#90
1!
#100
0!
#110
1!
#120
0!
#130
1!
#140
0!
#150
1!
#160
0!
#170
1!
#180
0!
#190
1!
#200
0!
#210
1!
#220
0!
#230
1!
#240
0!
#250
b1 $
1%
1!
#260
0!
#270
0%
1!
#280
0!
#290
1!
#300
0!
#310
1!
#320
0!
#330
1!
#340
0!
#350
0"
1!
#360
0!
#370
0)
1!
#380
0!
#390
1!
#400
0!
#410
1!
#420
0!
#430
1!
#440
0!
#450
1!
#460
0!
#470
1!
#480
0!
#490
1!
#500
0!
#510
1!
#520
0!
#530
1!
#540
0!
#550
1!
#560
0!
#570
b10 $
1%
1!
#580
0!
#590
0%
1!
#600
0!
#610
1!
#620
0!
#630
1!
#640
0!
#650
1!
#660
0!
#670
1"
1!
#680
0!
#690
1)
1!
#700
0!
#710
1!
#720
0!
#730
1!
#740
0!
#750
1!
#760
0!
#770
1!
#780
0!
#790
1!
#800
0!
#810
1!
#820
0!
#830
1!
#840
0!
#850
1!
#860
0!
#870
1!
#880
0!
#890
b11 $
1%
1!
#900
0!
#910
0%
1!
#920
0!
#930
1!
#940
0!
#950
1!
#960
0!
#970
1!
#980
0!
#990
0"
1!
#1000
0!
#1010
0)
1!
#1020
0!
#1030
1!
#1040
0!
#1050
1!
#1060
0!
#1070
1!
#1080
0!
#1090
1!
#1100
0!
#1110
1!
#1120
0!
#1130
1!
#1140
0!
#1150
1!
#1160
0!
#1170
1!
#1180
0!
#1190
1!
#1200
0!
#1210
b100 $
1%
1!
#1220
0!
#1230
0%
1!
#1240
0!
#1250
1!
#1260
0!
#1270
1!
#1280
0!
#1290
1!
#1300
0!
#1310
1"
1!
#1320
0!
#1330
1)
1!
#1340
0!
#1350
1!
#1360
0!
#1370
1!
#1380
0!
#1390
1!
#1400
0!
#1410
1!
#1420
0!
#1430
1!
#1440
0!
#1450
1!
#1460
0!
#1470
1!
#1480
0!
#1490
1!
#1500
0!
#1510
1!
#1520
0!
#1530
b101 $
1%
1!
#1540
0!
#1550
0%
1!
#1560
0!
#1570
1!
#1580
0!
#1590
1!
#1600
0!
#1610
1!
#1620
0!
#1630
0"
1!
#1640
0!
#1650
0)
1!
#1660
0!
#1670
1!
#1680
0!
#1690
1!
#1700
0!
#1710
1!
#1720
0!
#1730
1!
#1740
0!
#1750
1!
#1760
0!
#1770
1!
#1780
0!
#1790
1!
#1800
0!
#1810
1!
#1820
0!
#1830
1!
#1840
0!
#1850
b110 $
1%
1!
#1860
0!
#1870
0%
1!
#1880
0!
#1890
1!
#1900
0!
#1910
1!
#1920
0!
#1930
1!
#1940
0!
#1950
1"
1!
#1960
0!
#1970
1)
1!
#1980
0!
#1990
1!
#2000
0!
#2010
1!
#2020
0!
#2030
1!
#2040
0!
#2050
1!
#2060
0!
#2070
1!
#2080
0!
#2090
1!
#2100
0!
#2110
1!
#2120
0!
#2130
1!
#2140
0!
#2150
1!
#2160
0!
#2170
b111 $
1%
1!
#2180
0!
#2190
0%
1!
#2200
0!
#2210
1!
#2220
0!
#2230
1!
#2240
0!
#2250
1!
#2260
0!
#2270
0"
1!
#2280
0!
#2290
0)
1!
#2300
0!
#2310
1!
#2320
0!
#2330
1!
#2340
0!
#2350
1!
#2360
0!
#2370
1!
#2380
0!
#2390
1!
#2400
0!
#2410
1!
#2420
0!
#2430
1!
#2440
0!
#2450
1!
#2460
0!
#2470
1!
#2480
0!
#2490
b1000 $
1%
1!
#2500
0!
#2510
0%
1!
#2520
0!
#2530
1!
#2540
0!
#2550
1!
#2560
0!
#2570
1!
#2580
0!
#2590
1"
1!
#2600
0!
#2610
1)
1!
#2620
0!
#2630
1!
#2640
0!
#2650
1!
#2660
0!
#2670
1!
#2680
0!
#2690
1!
#2700
0!
#2710
1!
#2720
0!
#2730
1!
#2740
0!
#2750
1!
#2760
0!
#2770
1!
#2780
0!
#2790
1!
#2800
0!
#2810
b1001 $
1%
1!
#2820
0!
#2830
0%
1!
#2840
0!
#2850
1!
#2860
0!
#2870
1!
#2880
0!
#2890
1!
#2900
0!
#2910
0"
1!
#2920
0!
#2930
0)
1!
#2940
0!
#2950
1!
#2960
0!
#2970
1!
#2980
0!
#2990
1!
#3000
0!
#3010
1!
#3020
0!
#3030
1!
#3040
0!
#3050
1!
#3060
0!
#3070
1!
#3080
0!
#3090
1!
#3100
0!
#3110
1!
#3120
0!
#3130
b1010 $
1%
1!
#3140
0!
#3150
0%
1!
#3160
0!
#3170
1!
#3180
0!
#3190
1!
#3200
0!
#3210
1!
#3220
0!
#3230
1!
#3240
0!
#3250
1!
#3260
0!
#3270
1!
#3280
0!
#3290
1!
#3300
0!
#3310
1!
#3320
0!
#3330
1!
#3340
0!
#3350
1!
#3360
0!
#3370
1!
#3380
0!
#3390
1!
#3400
0!
#3410
1!
#3420
0!
#3430
1!
#3440
0!
#3450
b10101010 (
0&
b0 $
1%
1!
