Lab4/testBench/SIPO.v
module SIPO(data_in, sr_clk, reset, finish, data_out); // Serial In -> Parallel Out (10 bits)
	input sr_clk, reset;
	input data_in;
	input finish;
	output reg [7:0] data_out;

	reg [9:0] Q;

	always @(posedge sr_clk or reset) begin
		if (reset)
			Q <= 10'b0000000000;
		else begin
			Q[0] <= data_in;
			Q[1] <= Q[0];
			Q[2] <= Q[1];
			Q[3] <= Q[2];
			Q[4] <= Q[3];
			Q[5] <= Q[4];
			Q[6] <= Q[5];
			Q[7] <= Q[6];
			Q[8] <= Q[7];
			Q[9] <= Q[8];
		end
	end

	always @(posedge finish) begin
		data_out[0] <= Q[1];
		data_out[1] <= Q[2];
		data_out[2] <= Q[3];
		data_out[3] <= Q[4];
		data_out[4] <= Q[5];
		data_out[5] <= Q[6];
		data_out[6] <= Q[7];
		data_out[7] <= Q[8];
	end
endmodule

Lab4/testBench/SIPO_testBench.v
`include "SIPO.v"

module SIPO_testBench ();

    // connext the two modules
    wire [7:0] data_out;
    wire sr_clk, reset, finish, data_in;

    // declare an instance of the AND module
    SIPO sipo(data_in, sr_clk, reset, finish, data_out);

    // Running the GUI part of simulation
    SIPO_Tester aTester (data_in, sr_clk, reset, finish, data_out);

    // file for gtkwave

    initial
    begin
        $dumpfile("sipo.vcd");
        $dumpvars(1, sipo);
    end

endmodule

module SIPO_Tester (data_in, sr_clk, reset, finish, data_out);
    output reg data_in, sr_clk, reset, finish;
    input [7:0] data_out;

    parameter stimDelay = 10;

    // generate a clock
    always #(stimDelay/2) sr_clk = ~sr_clk;

    initial // Response
    begin
         sr_clk = 'b0;
    end

    always @(posedge sr_clk) // Stimulus
    begin
                    //reset = 'b0;
        #stimDelay    reset <= 1'b1;
        #stimDelay
        reset <= 1'b0;
	   finish <= 1'b0;
        #(10*stimDelay)
	  data_in <= 1'b1;
  
        #stimDelay
        #(8*stimDelay)
        
        data_in <= 1'b0;
        #stimDelay
        #(8*stimDelay)
        data_in <= 1'b0;
        #stimDelay
        
        #(8*stimDelay)
        
        data_in <= 1'b1;
        #stimDelay
        
        #(8*stimDelay)
        
        data_in <= 1'b0;
        #stimDelay
        
        #(8*stimDelay)
        
        data_in <= 1'b1;
        #stimDelay
        
        #(8*stimDelay)
        data_in <= 1'b1;
        #stimDelay
        
        #(8*stimDelay)
        
        data_in <= 1'b0;
        #stimDelay
        
        #(8*stimDelay)
        
        data_in <= 1'b1;
        #stimDelay
        
        #(8*stimDelay)
        data_in <= 1'b0;
        #stimDelay
        
	   finish <= 1'b1;        
        #(32*stimDelay)
        $stop;
        $finish;
    end

endmodule

Lab4/testBench/sipo.vcd
$date
	Mon May 30 16:56:58 2016
$end
$version
	Icarus Verilog
$end
$timescale
	1s
$end
$scope module SIPO_testBench $end
$scope module sipo $end
$var wire 1 ! data_in $end
$var wire 1 " finish $end
$var wire 1 # reset $end
$var wire 1 $ sr_clk $end
$var reg 10 % Q [9:0] $end
$var reg 8 & data_out [7:0] $end
$upscope $end
$upscope $end
$enddefinitions $end
#0
$dumpvars
bx &
bx %
0$
x#
x"
x!
$end
#5
1$
#10
0$
#15
1#
1$
#20
0$
#25
b1 %
0"
0#
1$
#30
0$
#35
b1x %
1$
#40
0$
#45
b1xx %
1$
#50
0$
#55
b1xxx %
1$
#60
0$
#65
b1xxxx %
1$
#70
0$
#75
b1xxxxx %
1$
#80
0$
#85
b1xxxxxx %
1$
#90
0$
#95
b1xxxxxxx %
1$
#100
0$
#105
b1xxxxxxxx %
1$
#110
0$
#115
b1xxxxxxxxx %
1$
#120
0$
#125
bx %
1!
1$
#130
0$
#135
bx1 %
1$
#140
0$
#145
bx11 %
1$
#150
0$
#155
bx111 %
1$
#160
0$
#165
bx1111 %
1$
#170
0$
#175
bx11111 %
1$
#180
0$
#185
bx111111 %
1$
#190
0$
#195
bx1111111 %
1$
#200
0$
#205
bx11111111 %
1$
#210
0$
#215
bx111111111 %
0!
1$
#220
0$
#225
b1111111110 %
1$
#230
0$
#235
b1111111100 %
1$
#240
0$
#245
b1111111000 %
1$
#250
0$
#255
b1111110000 %
1$
#260
0$
#265
b1111100000 %
1$
#270
0$
#275
b1111000000 %
1$
#280
0$
#285
b1110000000 %
1$
#290
0$
#295
b1100000000 %
1$
#300
0$
#305
b1000000000 %
1$
#310
0$
#315
b0 %
1$
#320
0$
#325
1$
#330
0$
#335
1$
#340
0$
#345
1$
#350
0$
#355
1$
#360
0$
#365
1$
#370
0$
#375
1$
#380
0$
#385
1$
#390
0$
#395
1!
1$
#400
0$
#405
b1 %
1$
#410
0$
#415
b11 %
1$
#420
0$
#425
b111 %
1$
#430
0$
#435
b1111 %
1$
#440
0$
#445
b11111 %
1$
#450
0$
#455
b111111 %
1$
#460
0$
#465
b1111111 %
1$
#470
0$
#475
b11111111 %
1$
#480
0$
#485
b111111111 %
0!
1$
#490
0$
#495
b1111111110 %
1$
#500
0$
#505
b1111111100 %
1$
#510
0$
#515
b1111111000 %
1$
#520
0$
#525
b1111110000 %
1$
#530
0$
#535
b1111100000 %
1$
#540
0$
#545
b1111000000 %
1$
#550
0$
#555
b1110000000 %
1$
#560
0$
#565
b1100000000 %
1$
#570
0$
#575
b1000000000 %
1!
1$
#580
0$
#585
b1 %
1$
#590
0$
#595
b11 %
1$
#600
0$
#605
b111 %
1$
#610
0$
#615
b1111 %
1$
#620
0$
#625
b11111 %
1$
#630
0$
#635
b111111 %
1$
#640
0$
#645
b1111111 %
1$
#650
0$
#655
b11111111 %
1$
#660
0$
#665
b111111111 %
1$
#670
0$
#675
b1111111111 %
1$
#680
0$
#685
1$
#690
0$
#695
1$
#700
0$
#705
1$
#710
0$
#715
1$
#720
0$
#725
1$
#730
0$
#735
1$
#740
0$
#745
1$
#750
0$
#755
0!
1$
#760
0$
#765
b1111111110 %
1$
#770
0$
#775
b1111111100 %
1$
#780
0$
#785
b1111111000 %
1$
#790
0$
#795
b1111110000 %
1$
#800
0$
#805
b1111100000 %
1$
#810
0$
#815
b1111000000 %
1$
#820
0$
#825
b1110000000 %
1$
#830
0$
#835
b1100000000 %
1$
#840
0$
#845
b1000000000 %
1!
1$
#850
0$
#855
b1 %
1$
#860
0$
#865
b11 %
1$
#870
0$
#875
b111 %
1$
#880
0$
#885
b1111 %
1$
#890
0$
#895
b11111 %
1$
#900
0$
#905
b111111 %
1$
#910
0$
#915
b1111111 %
1$
#920
0$
#925
b11111111 %
1$
#930
0$
#935
b111111111 %
0!
1$
#940
0$
#945
b11111111 &
b1111111110 %
1"
1$
#950
0$
#955
b1111111100 %
1$
#960
0$
#965
b1111111000 %
1$
#970
0$
#975
b1111110000 %
1$
#980
0$
#985
b1111100000 %
1$
#990
0$
#995
b1111000000 %
1$
#1000
0$
#1005
b1110000000 %
1$
#1010
0$
#1015
b1100000000 %
1$
#1020
0$
#1025
b1000000000 %
1$
#1030
0$
#1035
b0 %
1$
