Lab4/testBench/buffer.v
module buffer(input clk, reset, data_in, output data_out);
	reg q;
	assign data_out = q;
	 
	always @(posedge clk) begin
		if (reset) begin
			q <= 1;
		end else begin
			q <= data_in;
		end
	end
endmodule

Lab4/testBench/PISO.v
module PISO(sr_clk, clk, reset, data_in, data_out, load); // Parallel in -> Serial Out (10 bits)

	input sr_clk, clk, reset, load;
	input [7:0] data_in;
	output reg data_out;

	reg [9:0] Q_out;
	initial Q_out = 10'b1000000000;
	// reg bitStream;
	reg ps_load, ns_load;

	// Always block conducts parallel load
	always @(posedge clk) begin
			if (reset) begin
				Q_out[9:0] <= 10'b1000000000;
			end
			else if (load && ps_load != load) begin
				Q_out[9] = 1'b1;
				Q_out[8:1] = data_in;
				Q_out[0] = 1'b0;
			end
			else if (sr_clk) begin
				data_out = Q_out[9];
				Q_out[9] <= Q_out[8];
				Q_out[8] <= Q_out[7];
				Q_out[7] <= Q_out[6];
				Q_out[6] <= Q_out[5];
				Q_out[5] <= Q_out[4];
				Q_out[4] <= Q_out[3];
				Q_out[3] <= Q_out[2];
				Q_out[2] <= Q_out[1];
				Q_out[1] <= Q_out[0];
				Q_out[0] <= 1'b0;
		 end
		 ps_load <= ns_load;
		 ns_load <= load;
	end
endmodule

Lab4/testBench/BIC.v
module BIC(sr_clk, enable, reset, finish, state);
	input sr_clk;
	input enable;
	input reset;
	output reg finish;
	output reg [3:0] state;

	always @(posedge sr_clk or reset or ~enable) begin
		if (reset) begin
			state <= 4'b0000;
			finish <= 1'b0;
			end
		else if (enable) begin
			state <= state + 1'b1;
			finish <= finish;
			if (state == 4'b1010) begin
				finish <= 1'b1;
				state <= 4'b1010;
			end
		end
		else begin
			state <= 4'b0000;
			finish <= 1'b0;
			end
	end
endmodule

Lab4/testBench/BSC.v
module BSC(reset, enable, clk, sr_clk);
	input reset;
	input enable;
	input clk;
	output reg sr_clk;
	reg [3:0] state;
	always @(posedge clk) begin
		if (reset) begin
			state <= 4'b0000;
			sr_clk <= 1'b0;
		end
		else if (enable) begin
			state <= state + 1'b1;
			if (state == 4'b1000)
				sr_clk <= 1'b1;
			else 
				sr_clk <= 1'b0;
		end
		else begin
			state <= 4'b0000;
			sr_clk <= 1'b0;
		end
	end
endmodule

Lab4/testBench/transmit.sv
module transmit(data_in, enable, reset, clk, load, data_out, finish);
	input [7:0] data_in;
	input enable, load;
	input reset, clk;
	output data_out;
	output finish;

	wire sr_clk;
	wire data;
	wire [3:0] state;

	BSC bsc(.reset, .enable, .clk, .sr_clk);
	BIC bic(.sr_clk, .enable, .reset, .finish, .state);
	PISO piso(.sr_clk, .clk, .reset, .data_in, .data_out(data), .load);
	buffer b(.clk, .reset, .data_in(data), .data_out);
endmodule

Lab4/testBench/transmit_testBench.v
`include "BSC.v"
`include "BIC.v"
`include "buffer.v"
`include "PISO.v"
`include "transmit.sv"

module transmit_testBench ();

    // connext the two modules
    wire [7:0] data_in;
    wire enable, reset, clk, data_out, finish;

    // declare an instance of the AND module
    transmit tx (data_in, enable, reset, clk, load, data_out, finish);

    // Running the GUI part of simulation
    transmit_Tester aTester (data_in, enable, reset, clk, load, data_out, finish);

    // file for gtkwave

    initial
    begin
        $dumpfile("transmit.vcd");
        $dumpvars(1, tx);
    end

endmodule

module transmit_Tester (data_in, enable, reset, clk, load, data_out, finish);
    input data_out, finish;
    output reg [7:0] data_in;
    output reg enable, reset, clk, load;

    parameter stimDelay = 4;

    // generate a clock
    always #(stimDelay/2) clk = ~clk;

    initial // Response
    begin
        // $display("\t\t clk rst_n \t out \t   Time ");
        $monitor("\t %b ", data_out, finish, $time);
        clk = 'b0;
    end

    always @(posedge clk) // Stimulus
    begin
                    //reset = 'b0;
        #stimDelay    reset <= 1'b1;
        #stimDelay
        reset <= 1'b1;
        #stimDelay
        reset <= 1'b0;
        enable <= 1'b0;
        #(10*stimDelay)
        enable <= 1'b1;
        load <= 1'b0;
        #stimDelay
        load <= 1'b1;
        data_in <= 8'b01010100;
        #(500*stimDelay)
        enable <= 1'b0;
        #(10*stimDelay)
        load <= 1'b0;
        #(4*stimDelay)
        load <= 1'b1;
        enable <= 1'b1;
        #stimDelay
        data_in <= 8'b00110100;
        #(500*stimDelay)
        load <= 1'b0;
        enable <= 1'b0;
        $stop;
        $finish;
    end

endmodule

Lab4/testBench/transmit.vcd
$date
	Mon May 30 18:05:52 2016
$end
$version
	Icarus Verilog
$end
$timescale
	1s
$end
$scope module transmit_testBench $end
$scope module tx $end
$var wire 1 ! clk $end
$var wire 8 " data_in [7:0] $end
$var wire 1 # enable $end
$var wire 1 $ load $end
$var wire 1 % reset $end
$var wire 4 & state [3:0] $end
$var wire 1 ' sr_clk $end
$var wire 1 ( finish $end
$var wire 1 ) data_out $end
$var wire 1 * data $end
$upscope $end
$upscope $end
$enddefinitions $end
#0
$dumpvars
x*
x)
x(
x'
bx &
x%
x$
x#
bx "
0!
$end
#2
0'
1!
#4
0!
#6
0(
b0 &
1%
1!
#8
0!
#10
1)
1!
#12
0!
#14
0#
0%
1!
#16
0!
#18
x)
1!
#20
0!
#22
1!
#24
0!
#26
1!
#28
0!
#30
1!
#32
0!
#34
1!
#36
0!
#38
1!
#40
0!
#42
1!
#44
0!
#46
1!
#48
0!
#50
1!
#52
0!
#54
b1 &
0$
1#
1!
#56
0!
#58
b1010100 "
1$
1!
#60
0!
#62
1!
#64
0!
#66
1!
#68
0!
#70
1!
#72
0!
#74
1!
#76
0!
#78
1!
#80
0!
#82
1!
#84
0!
#86
1!
#88
0!
#90
b10 &
1'
1!
#92
0!
#94
1)
0'
1*
1!
#96
0!
#98
1!
#100
0!
#102
1!
#104
0!
#106
1!
#108
0!
#110
1!
#112
0!
#114
1!
#116
0!
#118
1!
#120
0!
#122
1!
#124
0!
#126
1!
#128
0!
#130
1!
#132
0!
#134
1!
#136
0!
#138
1!
#140
0!
#142
1!
#144
0!
#146
1!
#148
0!
#150
1!
#152
0!
#154
b11 &
1'
1!
#156
0!
#158
0)
0'
0*
1!
#160
0!
#162
1!
#164
0!
#166
1!
#168
0!
#170
1!
#172
0!
#174
1!
#176
0!
#178
1!
#180
0!
#182
1!
#184
0!
#186
1!
#188
0!
#190
1!
#192
0!
#194
1!
#196
0!
#198
1!
#200
0!
#202
1!
#204
0!
#206
1!
#208
0!
#210
1!
#212
0!
#214
1!
#216
0!
#218
b100 &
1'
1!
#220
0!
#222
1)
0'
1*
1!
#224
0!
#226
1!
#228
0!
#230
1!
#232
0!
#234
1!
#236
0!
#238
1!
#240
0!
#242
1!
#244
0!
#246
1!
#248
0!
#250
1!
#252
0!
#254
1!
#256
0!
#258
1!
#260
0!
#262
1!
#264
0!
#266
1!
#268
0!
#270
1!
#272
0!
#274
1!
#276
0!
#278
1!
#280
0!
#282
b101 &
1'
1!
#284
0!
#286
0)
0'
0*
1!
#288
0!
#290
1!
#292
0!
#294
1!
#296
0!
#298
1!
#300
0!
#302
1!
#304
0!
#306
1!
#308
0!
#310
1!
#312
0!
#314
1!
#316
0!
#318
1!
#320
0!
#322
1!
#324
0!
#326
1!
#328
0!
#330
1!
#332
0!
#334
1!
#336
0!
#338
1!
#340
0!
#342
1!
#344
0!
#346
b110 &
1'
1!
#348
0!
#350
1)
0'
1*
1!
#352
0!
#354
1!
#356
0!
#358
1!
#360
0!
#362
1!
#364
0!
#366
1!
#368
0!
#370
1!
#372
0!
#374
1!
#376
0!
#378
1!
#380
0!
#382
1!
#384
0!
#386
1!
#388
0!
#390
1!
#392
0!
#394
1!
#396
0!
#398
1!
#400
0!
#402
1!
#404
0!
#406
1!
#408
0!
#410
b111 &
1'
1!
#412
0!
#414
0)
0'
0*
1!
#416
0!
#418
1!
#420
0!
#422
1!
#424
0!
#426
1!
#428
0!
#430
1!
#432
0!
#434
1!
#436
0!
#438
1!
#440
0!
#442
1!
#444
0!
#446
1!
#448
0!
#450
1!
#452
0!
#454
1!
#456
0!
#458
1!
#460
0!
#462
1!
#464
0!
#466
1!
#468
0!
#470
1!
#472
0!
#474
b1000 &
1'
1!
#476
0!
#478
1)
0'
1*
1!
#480
0!
#482
1!
#484
0!
#486
1!
#488
0!
#490
1!
#492
0!
#494
1!
#496
0!
#498
1!
#500
0!
#502
1!
#504
0!
#506
1!
#508
0!
#510
1!
#512
0!
#514
1!
#516
0!
#518
1!
#520
0!
#522
1!
#524
0!
#526
1!
#528
0!
#530
1!
#532
0!
#534
1!
#536
0!
#538
b1001 &
1'
1!
#540
0!
#542
0)
0'
0*
1!
#544
0!
#546
1!
#548
0!
#550
1!
#552
0!
#554
1!
#556
0!
#558
1!
#560
0!
#562
1!
#564
0!
#566
1!
#568
0!
#570
1!
#572
0!
#574
1!
#576
0!
#578
1!
#580
0!
#582
1!
#584
0!
#586
1!
#588
0!
#590
1!
#592
0!
#594
1!
#596
0!
#598
1!
#600
0!
#602
b1010 &
1'
1!
#604
0!
#606
0'
1!
#608
0!
#610
1!
#612
0!
#614
1!
#616
0!
#618
1!
#620
0!
#622
1!
#624
0!
#626
1!
#628
0!
#630
1!
#632
0!
#634
1!
#636
0!
#638
1!
#640
0!
#642
1!
#644
0!
#646
1!
#648
0!
#650
1!
#652
0!
#654
1!
#656
0!
#658
1!
#660
0!
#662
1!
#664
0!
#666
1(
b1010 &
1'
1!
#668
0!
#670
0'
1!
#672
0!
#674
1!
#676
0!
#678
1!
#680
0!
#682
1!
#684
0!
#686
1!
#688
0!
#690
1!
#692
0!
#694
1!
#696
0!
#698
1!
#700
0!
#702
1!
#704
0!
#706
1!
#708
0!
#710
1!
#712
0!
#714
1!
#716
0!
#718
1!
#720
0!
#722
1!
#724
0!
#726
1!
#728
0!
#730
b1010 &
1'
1!
#732
0!
#734
0'
1!
#736
0!
#738
1!
#740
0!
#742
1!
#744
0!
#746
1!
#748
0!
#750
1!
#752
0!
#754
1!
#756
0!
#758
1!
#760
0!
#762
1!
#764
0!
#766
1!
#768
0!
#770
1!
#772
0!
#774
1!
#776
0!
#778
1!
#780
0!
#782
1!
#784
0!
#786
1!
#788
0!
#790
1!
#792
0!
#794
b1010 &
1'
1!
#796
0!
#798
0'
1!
#800
0!
#802
1!
#804
0!
#806
1!
#808
0!
#810
1!
#812
0!
#814
1!
#816
0!
#818
1!
#820
0!
#822
1!
#824
0!
#826
1!
#828
0!
#830
1!
#832
0!
#834
1!
#836
0!
#838
1!
#840
0!
#842
1!
#844
0!
#846
1!
#848
0!
#850
1!
#852
0!
#854
1!
#856
0!
#858
b1010 &
1'
1!
#860
0!
#862
0'
1!
#864
0!
#866
1!
#868
0!
#870
1!
#872
0!
#874
1!
#876
0!
#878
1!
#880
0!
#882
1!
#884
0!
#886
1!
#888
0!
#890
1!
#892
0!
#894
1!
#896
0!
#898
1!
#900
0!
#902
1!
#904
0!
#906
1!
#908
0!
#910
1!
#912
0!
#914
1!
#916
0!
#918
1!
#920
0!
#922
b1010 &
1'
1!
#924
0!
#926
0'
1!
#928
0!
#930
1!
#932
0!
#934
1!
#936
0!
#938
1!
#940
0!
#942
1!
#944
0!
#946
1!
#948
0!
#950
1!
#952
0!
#954
1!
#956
0!
#958
1!
#960
0!
#962
1!
#964
0!
#966
1!
#968
0!
#970
1!
#972
0!
#974
1!
#976
0!
#978
1!
#980
0!
#982
1!
#984
0!
#986
b1010 &
1'
1!
#988
0!
#990
0'
1!
#992
0!
#994
1!
#996
0!
#998
1!
#1000
0!
#1002
1!
#1004
0!
#1006
1!
#1008
0!
#1010
1!
#1012
0!
#1014
1!
#1016
0!
#1018
1!
#1020
0!
#1022
1!
#1024
0!
#1026
1!
#1028
0!
#1030
1!
#1032
0!
#1034
1!
#1036
0!
#1038
1!
#1040
0!
#1042
1!
#1044
0!
#1046
1!
#1048
0!
#1050
b1010 &
1'
1!
#1052
0!
#1054
0'
1!
#1056
0!
#1058
1!
#1060
0!
#1062
1!
#1064
0!
#1066
1!
#1068
0!
#1070
1!
#1072
0!
#1074
1!
#1076
0!
#1078
1!
#1080
0!
#1082
1!
#1084
0!
#1086
1!
#1088
0!
#1090
1!
#1092
0!
#1094
1!
#1096
0!
#1098
1!
#1100
0!
#1102
1!
#1104
0!
#1106
1!
#1108
0!
#1110
1!
#1112
0!
#1114
b1010 &
1'
1!
#1116
0!
#1118
0'
1!
#1120
0!
#1122
1!
#1124
0!
#1126
1!
#1128
0!
#1130
1!
#1132
0!
#1134
1!
#1136
0!
#1138
1!
#1140
0!
#1142
1!
#1144
0!
#1146
1!
#1148
0!
#1150
1!
#1152
0!
#1154
1!
#1156
0!
#1158
1!
#1160
0!
#1162
1!
#1164
0!
#1166
1!
#1168
0!
#1170
1!
#1172
0!
#1174
1!
#1176
0!
#1178
b1010 &
1'
1!
#1180
0!
#1182
0'
1!
#1184
0!
#1186
1!
#1188
0!
#1190
1!
#1192
0!
#1194
1!
#1196
0!
#1198
1!
#1200
0!
#1202
1!
#1204
0!
#1206
1!
#1208
0!
#1210
1!
#1212
0!
#1214
1!
#1216
0!
#1218
1!
#1220
0!
#1222
1!
#1224
0!
#1226
1!
#1228
0!
#1230
1!
#1232
0!
#1234
1!
#1236
0!
#1238
1!
#1240
0!
#1242
b1010 &
1'
1!
#1244
0!
#1246
0'
1!
#1248
0!
#1250
1!
#1252
0!
#1254
1!
#1256
0!
#1258
1!
#1260
0!
#1262
1!
#1264
0!
#1266
1!
#1268
0!
#1270
1!
#1272
0!
#1274
1!
#1276
0!
#1278
1!
#1280
0!
#1282
1!
#1284
0!
#1286
1!
#1288
0!
#1290
1!
#1292
0!
#1294
1!
#1296
0!
#1298
1!
#1300
0!
#1302
1!
#1304
0!
#1306
b1010 &
1'
1!
#1308
0!
#1310
0'
1!
#1312
0!
#1314
1!
#1316
0!
#1318
1!
#1320
0!
#1322
1!
#1324
0!
#1326
1!
#1328
0!
#1330
1!
#1332
0!
#1334
1!
#1336
0!
#1338
1!
#1340
0!
#1342
1!
#1344
0!
#1346
1!
#1348
0!
#1350
1!
#1352
0!
#1354
1!
#1356
0!
#1358
1!
#1360
0!
#1362
1!
#1364
0!
#1366
1!
#1368
0!
#1370
b1010 &
1'
1!
#1372
0!
#1374
0'
1!
#1376
0!
#1378
1!
#1380
0!
#1382
1!
#1384
0!
#1386
1!
#1388
0!
#1390
1!
#1392
0!
#1394
1!
#1396
0!
#1398
1!
#1400
0!
#1402
1!
#1404
0!
#1406
1!
#1408
0!
#1410
1!
#1412
0!
#1414
1!
#1416
0!
#1418
1!
#1420
0!
#1422
1!
#1424
0!
#1426
1!
#1428
0!
#1430
1!
#1432
0!
#1434
b1010 &
1'
1!
#1436
0!
#1438
0'
1!
#1440
0!
#1442
1!
#1444
0!
#1446
1!
#1448
0!
#1450
1!
#1452
0!
#1454
1!
#1456
0!
#1458
1!
#1460
0!
#1462
1!
#1464
0!
#1466
1!
#1468
0!
#1470
1!
#1472
0!
#1474
1!
#1476
0!
#1478
1!
#1480
0!
#1482
1!
#1484
0!
#1486
1!
#1488
0!
#1490
1!
#1492
0!
#1494
1!
#1496
0!
#1498
b1010 &
1'
1!
#1500
0!
#1502
0'
1!
#1504
0!
#1506
1!
#1508
0!
#1510
1!
#1512
0!
#1514
1!
#1516
0!
#1518
1!
#1520
0!
#1522
1!
#1524
0!
#1526
1!
#1528
0!
#1530
1!
#1532
0!
#1534
1!
#1536
0!
#1538
1!
#1540
0!
#1542
1!
#1544
0!
#1546
1!
#1548
0!
#1550
1!
#1552
0!
#1554
1!
#1556
0!
#1558
1!
#1560
0!
#1562
b1010 &
1'
1!
#1564
0!
#1566
0'
1!
#1568
0!
#1570
1!
#1572
0!
#1574
1!
#1576
0!
#1578
1!
#1580
0!
#1582
1!
#1584
0!
#1586
1!
#1588
0!
#1590
1!
#1592
0!
#1594
1!
#1596
0!
#1598
1!
#1600
0!
#1602
1!
#1604
0!
#1606
1!
#1608
0!
#1610
1!
#1612
0!
#1614
1!
#1616
0!
#1618
1!
#1620
0!
#1622
1!
#1624
0!
#1626
b1010 &
1'
1!
#1628
0!
#1630
0'
1!
#1632
0!
#1634
1!
#1636
0!
#1638
1!
#1640
0!
#1642
1!
#1644
0!
#1646
1!
#1648
0!
#1650
1!
#1652
0!
#1654
1!
#1656
0!
#1658
1!
#1660
0!
#1662
1!
#1664
0!
#1666
1!
#1668
0!
#1670
1!
#1672
0!
#1674
1!
#1676
0!
#1678
1!
#1680
0!
#1682
1!
#1684
0!
#1686
1!
#1688
0!
#1690
b1010 &
1'
1!
#1692
0!
#1694
0'
1!
#1696
0!
#1698
1!
#1700
0!
#1702
1!
#1704
0!
#1706
1!
#1708
0!
#1710
1!
#1712
0!
#1714
1!
#1716
0!
#1718
1!
#1720
0!
#1722
1!
#1724
0!
#1726
1!
#1728
0!
#1730
1!
#1732
0!
#1734
1!
#1736
0!
#1738
1!
#1740
0!
#1742
1!
#1744
0!
#1746
1!
#1748
0!
#1750
1!
#1752
0!
#1754
b1010 &
1'
1!
#1756
0!
#1758
0'
1!
#1760
0!
#1762
1!
#1764
0!
#1766
1!
#1768
0!
#1770
1!
#1772
0!
#1774
1!
#1776
0!
#1778
1!
#1780
0!
#1782
1!
#1784
0!
#1786
1!
#1788
0!
#1790
1!
#1792
0!
#1794
1!
#1796
0!
#1798
1!
#1800
0!
#1802
1!
#1804
0!
#1806
1!
#1808
0!
#1810
1!
#1812
0!
#1814
1!
#1816
0!
#1818
b1010 &
1'
1!
#1820
0!
#1822
0'
1!
#1824
0!
#1826
1!
#1828
0!
#1830
1!
#1832
0!
#1834
1!
#1836
0!
#1838
1!
#1840
0!
#1842
1!
#1844
0!
#1846
1!
#1848
0!
#1850
1!
#1852
0!
#1854
1!
#1856
0!
#1858
1!
#1860
0!
#1862
1!
#1864
0!
#1866
1!
#1868
0!
#1870
1!
#1872
0!
#1874
1!
#1876
0!
#1878
1!
#1880
0!
#1882
b1010 &
1'
1!
#1884
0!
#1886
0'
1!
#1888
0!
#1890
1!
#1892
0!
#1894
1!
#1896
0!
#1898
1!
#1900
0!
#1902
1!
#1904
0!
#1906
1!
#1908
0!
#1910
1!
#1912
0!
#1914
1!
#1916
0!
#1918
1!
#1920
0!
#1922
1!
#1924
0!
#1926
1!
#1928
0!
#1930
1!
#1932
0!
#1934
1!
#1936
0!
#1938
1!
#1940
0!
#1942
1!
#1944
0!
#1946
b1010 &
1'
1!
#1948
0!
#1950
0'
1!
#1952
0!
#1954
1!
#1956
0!
#1958
1!
#1960
0!
#1962
1!
#1964
0!
#1966
1!
#1968
0!
#1970
1!
#1972
0!
#1974
1!
#1976
0!
#1978
1!
#1980
0!
#1982
1!
#1984
0!
#1986
1!
#1988
0!
#1990
1!
#1992
0!
#1994
1!
#1996
0!
#1998
1!
#2000
0!
#2002
1!
#2004
0!
#2006
1!
#2008
0!
#2010
b1010 &
1'
1!
#2012
0!
#2014
0'
1!
#2016
0!
#2018
1!
#2020
0!
#2022
1!
#2024
0!
#2026
1!
#2028
0!
#2030
1!
#2032
0!
#2034
1!
#2036
0!
#2038
1!
#2040
0!
#2042
1!
#2044
0!
#2046
1!
#2048
0!
#2050
1!
#2052
0!
#2054
1!
#2056
0!
#2058
0(
b0 &
0#
1!
#2060
0!
#2062
1!
#2064
0!
#2066
1!
#2068
0!
#2070
1!
#2072
0!
#2074
1!
#2076
0!
#2078
1!
#2080
0!
#2082
1!
#2084
0!
#2086
1!
#2088
0!
#2090
1!
#2092
0!
#2094
1!
#2096
0!
#2098
0$
1!
#2100
0!
#2102
1!
#2104
0!
#2106
1!
#2108
0!
#2110
1!
#2112
0!
#2114
b1 &
1#
1$
1!
#2116
0!
#2118
b110100 "
1!
#2120
0!
#2122
1!
#2124
0!
#2126
1!
#2128
0!
#2130
1!
#2132
0!
#2134
1!
#2136
0!
#2138
1!
#2140
0!
#2142
1!
#2144
0!
#2146
1!
#2148
0!
#2150
b10 &
1'
1!
#2152
0!
#2154
0'
1*
1!
#2156
0!
#2158
1)
1!
#2160
0!
#2162
1!
#2164
0!
#2166
1!
#2168
0!
#2170
1!
#2172
0!
#2174
1!
#2176
0!
#2178
1!
#2180
0!
#2182
1!
#2184
0!
#2186
1!
#2188
0!
#2190
1!
#2192
0!
#2194
1!
#2196
0!
#2198
1!
#2200
0!
#2202
1!
#2204
0!
#2206
1!
#2208
0!
#2210
1!
#2212
0!
#2214
b11 &
1'
1!
#2216
0!
#2218
0'
0*
1!
#2220
0!
#2222
0)
1!
#2224
0!
#2226
1!
#2228
0!
#2230
1!
#2232
0!
#2234
1!
#2236
0!
#2238
1!
#2240
0!
#2242
1!
#2244
0!
#2246
1!
#2248
0!
#2250
1!
#2252
0!
#2254
1!
#2256
0!
#2258
1!
#2260
0!
#2262
1!
#2264
0!
#2266
1!
#2268
0!
#2270
1!
#2272
0!
#2274
1!
#2276
0!
#2278
b100 &
1'
1!
#2280
0!
#2282
0'
1!
#2284
0!
#2286
1!
#2288
0!
#2290
1!
#2292
0!
#2294
1!
#2296
0!
#2298
1!
#2300
0!
#2302
1!
#2304
0!
#2306
1!
#2308
0!
#2310
1!
#2312
0!
#2314
1!
#2316
0!
#2318
1!
#2320
0!
#2322
1!
#2324
0!
#2326
1!
#2328
0!
#2330
1!
#2332
0!
#2334
1!
#2336
0!
#2338
1!
#2340
0!
#2342
b101 &
1'
1!
#2344
0!
#2346
0'
1*
1!
#2348
0!
#2350
1)
1!
#2352
0!
#2354
1!
#2356
0!
#2358
1!
#2360
0!
#2362
1!
#2364
0!
#2366
1!
#2368
0!
#2370
1!
#2372
0!
#2374
1!
#2376
0!
#2378
1!
#2380
0!
#2382
1!
#2384
0!
#2386
1!
#2388
0!
#2390
1!
#2392
0!
#2394
1!
#2396
0!
#2398
1!
#2400
0!
#2402
1!
#2404
0!
#2406
b110 &
1'
1!
#2408
0!
#2410
0'
1!
#2412
0!
#2414
1!
#2416
0!
#2418
1!
#2420
0!
#2422
1!
#2424
0!
#2426
1!
#2428
0!
#2430
1!
#2432
0!
#2434
1!
#2436
0!
#2438
1!
#2440
0!
#2442
1!
#2444
0!
#2446
1!
#2448
0!
#2450
1!
#2452
0!
#2454
1!
#2456
0!
#2458
1!
#2460
0!
#2462
1!
#2464
0!
#2466
1!
#2468
0!
#2470
b111 &
1'
1!
#2472
0!
#2474
0'
0*
1!
#2476
0!
#2478
0)
1!
#2480
0!
#2482
1!
#2484
0!
#2486
1!
#2488
0!
#2490
1!
#2492
0!
#2494
1!
#2496
0!
#2498
1!
#2500
0!
#2502
1!
#2504
0!
#2506
1!
#2508
0!
#2510
1!
#2512
0!
#2514
1!
#2516
0!
#2518
1!
#2520
0!
#2522
1!
#2524
0!
#2526
1!
#2528
0!
#2530
1!
#2532
0!
#2534
b1000 &
1'
1!
#2536
0!
#2538
0'
1*
1!
#2540
0!
#2542
1)
1!
#2544
0!
#2546
1!
#2548
0!
#2550
1!
#2552
0!
#2554
1!
#2556
0!
#2558
1!
#2560
0!
#2562
1!
#2564
0!
#2566
1!
#2568
0!
#2570
1!
#2572
0!
#2574
1!
#2576
0!
#2578
1!
#2580
0!
#2582
1!
#2584
0!
#2586
1!
#2588
0!
#2590
1!
#2592
0!
#2594
1!
#2596
0!
#2598
b1001 &
1'
1!
#2600
0!
#2602
0'
0*
1!
#2604
0!
#2606
0)
1!
#2608
0!
#2610
1!
#2612
0!
#2614
1!
#2616
0!
#2618
1!
#2620
0!
#2622
1!
#2624
0!
#2626
1!
#2628
0!
#2630
1!
#2632
0!
#2634
1!
#2636
0!
#2638
1!
#2640
0!
#2642
1!
#2644
0!
#2646
1!
#2648
0!
#2650
1!
#2652
0!
#2654
1!
#2656
0!
#2658
1!
#2660
0!
#2662
b1010 &
1'
1!
#2664
0!
#2666
0'
1!
#2668
0!
#2670
1!
#2672
0!
#2674
1!
#2676
0!
#2678
1!
#2680
0!
#2682
1!
#2684
0!
#2686
1!
#2688
0!
#2690
1!
#2692
0!
#2694
1!
#2696
0!
#2698
1!
#2700
0!
#2702
1!
#2704
0!
#2706
1!
#2708
0!
#2710
1!
#2712
0!
#2714
1!
#2716
0!
#2718
1!
#2720
0!
#2722
1!
#2724
0!
#2726
1(
b1010 &
1'
1!
#2728
0!
#2730
0'
1!
#2732
0!
#2734
1!
#2736
0!
#2738
1!
#2740
0!
#2742
1!
#2744
0!
#2746
1!
#2748
0!
#2750
1!
#2752
0!
#2754
1!
#2756
0!
#2758
1!
#2760
0!
#2762
1!
#2764
0!
#2766
1!
#2768
0!
#2770
1!
#2772
0!
#2774
1!
#2776
0!
#2778
1!
#2780
0!
#2782
1!
#2784
0!
#2786
1!
#2788
0!
#2790
b1010 &
1'
1!
#2792
0!
#2794
0'
1!
#2796
0!
#2798
1!
#2800
0!
#2802
1!
#2804
0!
#2806
1!
#2808
0!
#2810
1!
#2812
0!
#2814
1!
#2816
0!
#2818
1!
#2820
0!
#2822
1!
#2824
0!
#2826
1!
#2828
0!
#2830
1!
#2832
0!
#2834
1!
#2836
0!
#2838
1!
#2840
0!
#2842
1!
#2844
0!
#2846
1!
#2848
0!
#2850
1!
#2852
0!
#2854
b1010 &
1'
1!
#2856
0!
#2858
0'
1!
#2860
0!
#2862
1!
#2864
0!
#2866
1!
#2868
0!
#2870
1!
#2872
0!
#2874
1!
#2876
0!
#2878
1!
#2880
0!
#2882
1!
#2884
0!
#2886
1!
#2888
0!
#2890
1!
#2892
0!
#2894
1!
#2896
0!
#2898
1!
#2900
0!
#2902
1!
#2904
0!
#2906
1!
#2908
0!
#2910
1!
#2912
0!
#2914
1!
#2916
0!
#2918
b1010 &
1'
1!
#2920
0!
#2922
0'
1!
#2924
0!
#2926
1!
#2928
0!
#2930
1!
#2932
0!
#2934
1!
#2936
0!
#2938
1!
#2940
0!
#2942
1!
#2944
0!
#2946
1!
#2948
0!
#2950
1!
#2952
0!
#2954
1!
#2956
0!
#2958
1!
#2960
0!
#2962
1!
#2964
0!
#2966
1!
#2968
0!
#2970
1!
#2972
0!
#2974
1!
#2976
0!
#2978
1!
#2980
0!
#2982
b1010 &
1'
1!
#2984
0!
#2986
0'
1!
#2988
0!
#2990
1!
#2992
0!
#2994
1!
#2996
0!
#2998
1!
#3000
0!
#3002
1!
#3004
0!
#3006
1!
#3008
0!
#3010
1!
#3012
0!
#3014
1!
#3016
0!
#3018
1!
#3020
0!
#3022
1!
#3024
0!
#3026
1!
#3028
0!
#3030
1!
#3032
0!
#3034
1!
#3036
0!
#3038
1!
#3040
0!
#3042
1!
#3044
0!
#3046
b1010 &
1'
1!
#3048
0!
#3050
0'
1!
#3052
0!
#3054
1!
#3056
0!
#3058
1!
#3060
0!
#3062
1!
#3064
0!
#3066
1!
#3068
0!
#3070
1!
#3072
0!
#3074
1!
#3076
0!
#3078
1!
#3080
0!
#3082
1!
#3084
0!
#3086
1!
#3088
0!
#3090
1!
#3092
0!
#3094
1!
#3096
0!
#3098
1!
#3100
0!
#3102
1!
#3104
0!
#3106
1!
#3108
0!
#3110
b1010 &
1'
1!
#3112
0!
#3114
0'
1!
#3116
0!
#3118
1!
#3120
0!
#3122
1!
#3124
0!
#3126
1!
#3128
0!
#3130
1!
#3132
0!
#3134
1!
#3136
0!
#3138
1!
#3140
0!
#3142
1!
#3144
0!
#3146
1!
#3148
0!
#3150
1!
#3152
0!
#3154
1!
#3156
0!
#3158
1!
#3160
0!
#3162
1!
#3164
0!
#3166
1!
#3168
0!
#3170
1!
#3172
0!
#3174
b1010 &
1'
1!
#3176
0!
#3178
0'
1!
#3180
0!
#3182
1!
#3184
0!
#3186
1!
#3188
0!
#3190
1!
#3192
0!
#3194
1!
#3196
0!
#3198
1!
#3200
0!
#3202
1!
#3204
0!
#3206
1!
#3208
0!
#3210
1!
#3212
0!
#3214
1!
#3216
0!
#3218
1!
#3220
0!
#3222
1!
#3224
0!
#3226
1!
#3228
0!
#3230
1!
#3232
0!
#3234
1!
#3236
0!
#3238
b1010 &
1'
1!
#3240
0!
#3242
0'
1!
#3244
0!
#3246
1!
#3248
0!
#3250
1!
#3252
0!
#3254
1!
#3256
0!
#3258
1!
#3260
0!
#3262
1!
#3264
0!
#3266
1!
#3268
0!
#3270
1!
#3272
0!
#3274
1!
#3276
0!
#3278
1!
#3280
0!
#3282
1!
#3284
0!
#3286
1!
#3288
0!
#3290
1!
#3292
0!
#3294
1!
#3296
0!
#3298
1!
#3300
0!
#3302
b1010 &
1'
1!
#3304
0!
#3306
0'
1!
#3308
0!
#3310
1!
#3312
0!
#3314
1!
#3316
0!
#3318
1!
#3320
0!
#3322
1!
#3324
0!
#3326
1!
#3328
0!
#3330
1!
#3332
0!
#3334
1!
#3336
0!
#3338
1!
#3340
0!
#3342
1!
#3344
0!
#3346
1!
#3348
0!
#3350
1!
#3352
0!
#3354
1!
#3356
0!
#3358
1!
#3360
0!
#3362
1!
#3364
0!
#3366
b1010 &
1'
1!
#3368
0!
#3370
0'
1!
#3372
0!
#3374
1!
#3376
0!
#3378
1!
#3380
0!
#3382
1!
#3384
0!
#3386
1!
#3388
0!
#3390
1!
#3392
0!
#3394
1!
#3396
0!
#3398
1!
#3400
0!
#3402
1!
#3404
0!
#3406
1!
#3408
0!
#3410
1!
#3412
0!
#3414
1!
#3416
0!
#3418
1!
#3420
0!
#3422
1!
#3424
0!
#3426
1!
#3428
0!
#3430
b1010 &
1'
1!
#3432
0!
#3434
0'
1!
#3436
0!
#3438
1!
#3440
0!
#3442
1!
#3444
0!
#3446
1!
#3448
0!
#3450
1!
#3452
0!
#3454
1!
#3456
0!
#3458
1!
#3460
0!
#3462
1!
#3464
0!
#3466
1!
#3468
0!
#3470
1!
#3472
0!
#3474
1!
#3476
0!
#3478
1!
#3480
0!
#3482
1!
#3484
0!
#3486
1!
#3488
0!
#3490
1!
#3492
0!
#3494
b1010 &
1'
1!
